{
  "generated_at_utc": "2025-08-18T11:14:24.545458Z",
  "observer": "geocentric Earth",
  "source": "JPL Horizons (fallback: Swiss for majors)",
  "objects": [
    {
      "id": "10",
      "targetname": "Sun",
      "ecl_lon_deg": 145.77341640971045,
      "ecl_lat_deg": 0.0001335157330177737,
      "source": "swiss"
    },
    {
      "id": "301",
      "targetname": "Moon",
      "ecl_lon_deg": 85.42314926327997,
      "ecl_lat_deg": 5.198057901223229,
      "source": "swiss"
    },
    {
      "id": "199",
      "targetname": "Mercury",
      "ecl_lon_deg": 127.27031072294717,
      "ecl_lat_deg": -1.122617729282522,
      "source": "swiss"
    },
    {
      "id": "299",
      "targetname": "Venus",
      "ecl_lon_deg": 111.42097607989894,
      "ecl_lat_deg": -0.5872065308917529,
      "source": "swiss"
    },
    {
      "id": "499",
      "targetname": "Mars",
      "ecl_lon_deg": 187.2237951449996,
      "ecl_lat_deg": 0.40636062612755924,
      "source": "swiss"
    },
    {
      "id": "599",
      "targetname": "Jupiter",
      "ecl_lon_deg": 105.3158334454789,
      "ecl_lat_deg": -0.05422462680540264,
      "source": "swiss"
    },
    {
      "id": "699",
      "targetname": "Saturn",
      "ecl_lon_deg": 0.8748980928776218,
      "ecl_lat_deg": -2.4401800898553283,
      "source": "swiss"
    },
    {
      "id": "799",
      "targetname": "Uranus",
      "ecl_lon_deg": 61.315774063676905,
      "ecl_lat_deg": -0.20946697840088896,
      "source": "swiss"
    },
    {
      "id": "899",
      "targetname": "Neptune",
      "ecl_lon_deg": 1.675010783791793,
      "ecl_lat_deg": -1.3608091232056188,
      "source": "swiss"
    },
    {
      "id": "999",
      "targetname": "Pluto",
      "ecl_lon_deg": 302.03966424428404,
      "ecl_lat_deg": -3.779489022382179,
      "source": "swiss"
    },
    {
      "id": "Regulus",
      "targetname": "Regulus (Alpha Leo)",
      "ra_deg": 152.0929625,
      "dec_deg": 11.9672083,
      "epoch": "J2000",
      "source": "fixed"
    },
    {
      "id": "Spica",
      "targetname": "Spica (Alpha Vir)",
      "ra_deg": 201.2982475,
      "dec_deg": -11.1613194,
      "epoch": "J2000",
      "source": "fixed"
    },
    {
      "id": "Sirius",
      "targetname": "Sirius (Alpha CMa)",
      "ra_deg": 101.28715533,
      "dec_deg": -16.71611586,
      "epoch": "J2000",
      "source": "fixed"
    },
    {
      "id": "Aldebaran",
      "targetname": "Aldebaran (Alpha Tau)",
      "ra_deg": 68.9801625,
      "dec_deg": 16.50930278,
      "epoch": "J2000",
      "source": "fixed"
    },
    {
      "id": "ASC@Tommy",
      "targetname": "ASC (Tommy)",
      "datetime_utc": "2025-08-18T11:14:24.545458Z",
      "ecl_lon_deg": 157.7127396281598,
      "source": "swiss"
    },
    {
      "id": "MC@Tommy",
      "targetname": "MC (Tommy)",
      "datetime_utc": "2025-08-18T11:14:24.545458Z",
      "ecl_lon_deg": 63.813349701778854,
      "source": "swiss"
    },
    {
      "id": "Houses@Tommy",
      "targetname": "Houses (Tommy)",
      "datetime_utc": "2025-08-18T11:14:24.545458Z",
      "houses_deg": [
        181.5772283452535,
        210.4979357970611,
        243.81334970177886,
        278.31567743861945,
        310.0590236619605,
        337.7127396281598,
        1.577228345253502,
        30.497935797061132,
        63.813349701778854,
        98.31567743861946,
        130.0590236619605
      ],
      "source": "swiss"
    },
    {
      "id": "PartOfFortune@Tommy",
      "targetname": "Part of Fortune (Tommy)",
      "datetime_utc": "2025-08-18T11:14:24.545458Z",
      "ecl_lon_deg": 97.36247248172933,
      "branch": "day",
      "source": "swiss+legacy"
    },
    {
      "id": "PartOfSpirit@Tommy",
      "targetname": "Part of Spirit (Tommy)",
      "datetime_utc": "2025-08-18T11:14:24.545458Z",
      "ecl_lon_deg": 218.0630067745903,
      "branch": "day",
      "source": "swiss+legacy"
    },
    {
      "id": "ASC@Milena",
      "targetname": "ASC (Milena)",
      "datetime_utc": "2025-08-18T11:14:24.545458Z",
      "ecl_lon_deg": 120.89568047961998,
      "source": "swiss"
    },
    {
      "id": "MC@Milena",
      "targetname": "MC (Milena)",
      "datetime_utc": "2025-08-18T11:14:24.545458Z",
      "ecl_lon_deg": 17.256974300172367,
      "source": "swiss"
    },
    {
      "id": "Houses@Milena",
      "targetname": "Houses (Milena)",
      "datetime_utc": "2025-08-18T11:14:24.545458Z",
      "houses_deg": [
        141.53451066036013,
        166.2891903308351,
        197.25697430017237,
        233.61936449242995,
        269.7189586277976,
        300.89568047961995,
        321.5345106603601,
        346.28919033083514,
        17.256974300172367,
        53.61936449242994,
        89.71895862779759
      ],
      "source": "swiss"
    },
    {
      "id": "PartOfFortune@Milena",
      "targetname": "Part of Fortune (Milena)",
      "datetime_utc": "2025-08-18T11:14:24.545458Z",
      "ecl_lon_deg": 181.24594762605045,
      "branch": "night",
      "source": "swiss+legacy"
    },
    {
      "id": "PartOfSpirit@Milena",
      "targetname": "Part of Spirit (Milena)",
      "datetime_utc": "2025-08-18T11:14:24.545458Z",
      "ecl_lon_deg": 60.54541333318949,
      "branch": "night",
      "source": "swiss+legacy"
    },
    {
      "id": "ASC@Christine",
      "targetname": "ASC (Christine)",
      "datetime_utc": "2025-08-18T11:14:24.545458Z",
      "ecl_lon_deg": 158.21115443063502,
      "source": "swiss"
    },
    {
      "id": "MC@Christine",
      "targetname": "MC (Christine)",
      "datetime_utc": "2025-08-18T11:14:24.545458Z",
      "ecl_lon_deg": 64.44626283770526,
      "source": "swiss"
    },
    {
      "id": "Houses@Christine",
      "targetname": "Houses (Christine)",
      "datetime_utc": "2025-08-18T11:14:24.545458Z",
      "houses_deg": [
        182.15981080046853,
        211.13839057822182,
        244.44626283770526,
        278.8863150462764,
        310.5793599537647,
        338.211154430635,
        2.1598108004685628,
        31.138390578221788,
        64.44626283770526,
        98.88631504627641,
        130.5793599537647
      ],
      "source": "swiss"
    },
    {
      "id": "PartOfFortune@Christine",
      "targetname": "Part of Fortune (Christine)",
      "datetime_utc": "2025-08-18T11:14:24.545458Z",
      "ecl_lon_deg": 97.86088728420455,
      "branch": "day",
      "source": "swiss+legacy"
    },
    {
      "id": "PartOfSpirit@Christine",
      "targetname": "Part of Spirit (Christine)",
      "datetime_utc": "2025-08-18T11:14:24.545458Z",
      "ecl_lon_deg": 218.56142157706546,
      "branch": "day",
      "source": "swiss+legacy"
    }
  ]
}